autoip/__init__.py
autoip/autoip.py
autoip/banner.py
autoip/utils.py
autoip-1.0.1.dist-info/LICENSE
autoip-1.0.1.dist-info/METADATA
autoip-1.0.1.dist-info/WHEEL
autoip-1.0.1.dist-info/entry_points.txt
autoip-1.0.1.dist-info/top_level.txt
autoip-1.0.1.dist-info/RECORD
