Metadata-Version: 2.1
Name: autoip
Version: 1.0.1
Summary: AutoIP - Automate IP address changes using Tor
Home-page: https://github.com/ByteBreac/autoip
Author: Fidal
Author-email: mrfidal@proton.me
Classifier: Programming Language :: Python :: 3
Classifier: License :: OSI Approved :: MIT License
Classifier: Operating System :: OS Independent
Requires-Python: >=3.6
License-File: LICENSE
Requires-Dist: requests
Requires-Dist: validlink
Requires-Dist: requests[socks]
